birdhousebuilder.recipe.docker-0.4.8-py2.7-nspkg.pth
birdhousebuilder/recipe/docker/Dockerfile
birdhousebuilder/recipe/docker/__init__.py
birdhousebuilder/recipe/docker/custom.cfg
birdhousebuilder/recipe/docker/dot_dockerignore
birdhousebuilder.recipe.docker-0.4.8.dist-info/DESCRIPTION.rst
birdhousebuilder.recipe.docker-0.4.8.dist-info/METADATA
birdhousebuilder.recipe.docker-0.4.8.dist-info/RECORD
birdhousebuilder.recipe.docker-0.4.8.dist-info/WHEEL
birdhousebuilder.recipe.docker-0.4.8.dist-info/entry_points.txt
birdhousebuilder.recipe.docker-0.4.8.dist-info/metadata.json
birdhousebuilder.recipe.docker-0.4.8.dist-info/namespace_packages.txt
birdhousebuilder.recipe.docker-0.4.8.dist-info/pbr.json
birdhousebuilder.recipe.docker-0.4.8.dist-info/top_level.txt
