Metadata-Version: 2.0
Name: birdhousebuilder.recipe.docker
Version: 0.4.8
Summary: A Buildout recipe to generate a Dockerfile for Birdhouse applications.
Home-page: https://github.com/bird-house/birdhousebuilder.recipe.docker
Author: Birdhouse
Author-email: UNKNOWN
License: Apache License v2.0
Keywords: buildout recipe birdhouse
Platform: UNKNOWN
Classifier: Framework :: Buildout
Classifier: Intended Audience :: Developers
Classifier: Topic :: Software Development :: Build Tools
Classifier: Topic :: Software Development :: Libraries :: Python Modules
Requires-Dist: Mako
Requires-Dist: setuptools
Requires-Dist: zc.buildout
Provides-Extra: tests
Requires-Dist: manuel; extra == 'tests'
Requires-Dist: zc.buildout; extra == 'tests'
Requires-Dist: zope.testing; extra == 'tests'
